firestore/__init__.py
firestore/db.py
firestore/entity.py
firestore/query.py
firestore_entities-0.2.5.dist-info/LICENSE
firestore_entities-0.2.5.dist-info/METADATA
firestore_entities-0.2.5.dist-info/WHEEL
firestore_entities-0.2.5.dist-info/top_level.txt
firestore_entities-0.2.5.dist-info/RECORD
