Metadata-Version: 2.1
Name: firestore-entities
Version: 0.2.5
Summary: Implementation of entities concept on top of Google cloud firestore
Home-page: https://github.com/Billcountry/firestore-entities
Author: Billcountry Mwaniki
Author-email: me@billcountry.tech
License: UNKNOWN
Platform: UNKNOWN
Classifier: Programming Language :: Python :: 3
Classifier: License :: OSI Approved :: MIT License
Classifier: Operating System :: OS Independent
Requires-Dist: google-cloud-firestore
